{
    "roots": [
      "."
    ],
    "moduleDirectories": [
      "node_modules"
    ],
    "coverageDirectory": "coverage",
    "coveragePathIgnorePatterns": [
        "<rootDir>/node_modules/"
    ],
    "testPathIgnorePatterns": [
      "<rootDir>/tests/helpers/"
    ],
    "testRegex": [
      "(/tests/.*|(\\.|/)spec)\\.[jt]sx?$"
    ],
    "collectCoverageFrom": [
      "src/**/*.js"
    ],
    "coverageReporters": [
      "html",
      "lcov"
    ],
    "coverageThreshold": {
      "global": {
        "statements": 98,
        "branches": 98,
        "functions": 98,
        "lines": 98
      },
      "./**/*.js": {
        "statements": 98,
        "branches": 98,
        "functions": 98,
        "lines": 98
      }
    }
}